isitdarkoutside/__init__.py
isitdarkoutside/command_line.py
isitdarkoutside/isitdarkoutside.py
isitdarkoutside-0.2.0.dist-info/DESCRIPTION.rst
isitdarkoutside-0.2.0.dist-info/METADATA
isitdarkoutside-0.2.0.dist-info/RECORD
isitdarkoutside-0.2.0.dist-info/WHEEL
isitdarkoutside-0.2.0.dist-info/entry_points.txt
isitdarkoutside-0.2.0.dist-info/metadata.json
isitdarkoutside-0.2.0.dist-info/top_level.txt
