Metadata-Version: 2.0
Name: isitdarkoutside
Version: 0.2.0
Summary: A simple tool which makes use of location and sunrise/sunset timings to determine whether it's dark outside or not.
Home-page: UNKNOWN
Author: Aaditya Prasad
Author-email: aadityaprasad04@gmail.com
License: MIT
Platform: UNKNOWN
Classifier: Development Status :: 3 - Alpha
Classifier: License :: OSI Approved :: MIT License
Classifier: Programming Language :: Python :: 2 :: Only
Classifier: Topic :: System :: Networking :: Time Synchronization
Requires-Dist: geocoder
Requires-Dist: python-dateutil
